data_tests/__init__.py
data_tests/admin.py
data_tests/apps.py
data_tests/constants.py
data_tests/models.py
data_tests/registry.py
data_tests/urls.py
data_tests/views.py
data_tests/management/__init__.py
data_tests/management/commands/__init__.py
data_tests/management/commands/rundatatests.py
data_tests/migrations/0001_initial.py
data_tests/migrations/0002_auto_20191119_1055.py
data_tests/migrations/0003_auto_20200105_2116.py
data_tests/migrations/__init__.py
data_tests/static/css/validated.css
data_tests/static/js/validated.js
data_tests/templates/data_tests/base.html
django_data_tests-0.6.0.dist-info/DESCRIPTION.rst
django_data_tests-0.6.0.dist-info/METADATA
django_data_tests-0.6.0.dist-info/RECORD
django_data_tests-0.6.0.dist-info/WHEEL
django_data_tests-0.6.0.dist-info/metadata.json
django_data_tests-0.6.0.dist-info/top_level.txt
