Metadata-Version: 2.0
Name: django-data-tests
Version: 0.6.0
Summary: A Django app for specifying validation tests on data in your database.
Home-page: https://github.com/andrewbird2/django-data-tests
Author: Andrew Bird
Author-email: andrewbirdemail@gmail.com
License: MIT
Keywords: django-data-tests
Platform: UNKNOWN
Classifier: Development Status :: 3 - Alpha
Classifier: Framework :: Django :: 1.11
Classifier: Framework :: Django :: 2.0
Classifier: Intended Audience :: Developers
Classifier: License :: OSI Approved :: BSD License
Classifier: Natural Language :: English
Classifier: Programming Language :: Python :: 2
Classifier: Programming Language :: Python :: 2.7
Classifier: Programming Language :: Python :: 3
Classifier: Programming Language :: Python :: 3.4
Classifier: Programming Language :: Python :: 3.5
Classifier: Programming Language :: Python :: 3.6
Requires-Dist: django-model-utils (>=2.0)
